{"paths": [
{"uid": "P-147-71-3-0", "weight": 0.25, "r": 0, "g": 0, "b": 0, 
	"vertices": [
		{"obj_name": 1, "r": 86.5054, "g": 66.5931, "b": 161.233},
		{"obj_name": 0, "r": 98.9896, "g": 71.5837, "b": 115.282},
		{"obj_name": 2, "r": 1.0258, "g": 44.3818, "b": 9.86005},
		{"obj_name": 0, "r": 15.0446, "g": 50.5089, "b": 0.00658071},
		{"obj_name": 5, "r": 1.0146, "g": 58.876, "b": 30.6746},
		{"obj_name": 7, "r": 9.26695, "g": 81.5911, "b": 92.5932},
		{"obj_name": 1, "r": 68.6931, "g": 28.7056, "b": 88.2335}
	]
},
{"uid": "P-147-71-3-1", "weight": 0.25, "r": 0, "g": 0, "b": 0, 
	"vertices": [
		{"obj_name": 1, "r": 86.3499, "g": 66.4052, "b": 161.171},
		{"obj_name": 0, "r": 98.9899, "g": 71.4143, "b": 114.425},
		{"obj_name": 3, "r": 1.02003, "g": 79.2443, "b": 131.88},
		{"obj_name": 1, "r": 97.1237, "g": 55.8081, "b": 169.988},
		{"obj_name": 5, "r": 98.9664, "g": 56.8779, "b": 161.975},
		{"obj_name": 1, "r": 71.2486, "g": 81.5844, "b": 133.179}
	]
},
{"uid": "P-147-71-3-2", "weight": 0.25, "r": 0, "g": 0, "b": 0, 
	"vertices": [
		{"obj_name": 1, "r": 86.3783, "g": 66.8574, "b": 161.228},
		{"obj_name": 5, "r": 98.9897, "g": 72.0081, "b": 114.645},
		{"obj_name": 0, "r": 84.1383, "g": 81.5941, "b": 78.6883},
		{"obj_name": 5, "r": 1.02229, "g": 29.3384, "b": 15.8229},
		{"obj_name": 1, "r": 83.7598, "g": 81.5941, "b": 74.7645},
		{"obj_name": 7, "r": 98.9996, "g": 45.224, "b": 74.1835},
		{"obj_name": 0, "r": 69.079, "g": 31.2118, "b": 71.6408},
		{"obj_name": 4, "r": 1.00512, "g": 18.1138, "b": 59.0165}
	]
},
{"uid": "P-147-71-3-3", "weight": 0.25, "r": 0, "g": 0, "b": 0, 
	"vertices": [
		{"obj_name": 1, "r": 86.3059, "g": 66.6438, "b": 161.185},
		{"obj_name": 4, "r": 98.9899, "g": 71.7599, "b": 114.225},
		{"obj_name": 5, "r": 35.6764, "g": 0.0204409, "b": 19.2861},
		{"obj_name": 3, "r": 75.7242, "g": 81.5826, "b": 134.74},
		{"obj_name": 0, "r": 73.0424, "g": 27.4682, "b": 169.996},
		{"obj_name": 4, "r": 1.00319, "g": 34.0597, "b": 105.936}
	]
},
{"uid": "P-147-71-3-4", "weight": 0.25, "r": 0, "g": 0, "b": 0, 
	"vertices": [
		{"obj_name": 1, "r": 86.6552, "g": 66.3502, "b": 161.248},
		{"obj_name": 5, "r": 98.9895, "g": 71.179, "b": 116.039},
		{"obj_name": 1, "r": 82.5427, "g": 81.5787, "b": 138.258},
		{"obj_name": 5, "r": 98.9772, "g": 54.8071, "b": 147.606},
		{"obj_name": 3, "r": 35.4851, "g": 81.591, "b": 121.361},
		{"obj_name": 5, "r": 53.7518, "g": 0.256167, "b": 169.992},
		{"obj_name": 2, "r": 63.1283, "g": 81.5946, "b": 51.5348}
	]
},
{"uid": "P-147-71-3-5", "weight": 0.25, "r": 0, "g": 0, "b": 0, 
	"vertices": [
		{"obj_name": 1, "r": 86.1311, "g": 66.6036, "b": 161.133},
		{"obj_name": 2, "r": 98.9902, "g": 71.801, "b": 113.276},
		{"obj_name": 1, "r": 54.0878, "g": 64.678, "b": 0.00293434},
		{"obj_name": 3, "r": 98.9995, "g": 50.4875, "b": 78.6251},
		{"obj_name": 5, "r": 67.436, "g": 76.8618, "b": 169.992},
		{"obj_name": 4, "r": 66.718, "g": 81.5676, "b": 160.382},
		{"obj_name": 3, "r": 29.1356, "g": 0.0155515, "b": 133.32}
	]
},
{"uid": "P-147-71-3-6", "weight": 0.25, "r": 0, "g": 0, "b": 0, 
	"vertices": [
		{"obj_name": 1, "r": 86.2386, "g": 66.8372, "b": 161.188},
		{"obj_name": 3, "r": 98.9899, "g": 72.058, "b": 113.892},
		{"obj_name": 2, "r": 79.5221, "g": 46.5858, "b": 169.995},
		{"obj_name": 0, "r": 18.9548, "g": 28.6369, "b": 0.00555874},
		{"obj_name": 2, "r": 1.01106, "g": 14.1164, "b": 42.8656},
		{"obj_name": 0, "r": 27.7634, "g": 21.742, "b": 0.00428838},
		{"obj_name": 1, "r": 1.0203, "g": 23.9138, "b": 20.166},
		{"obj_name": 0, "r": 98.9825, "g": 67.7412, "b": 134.285},
		{"obj_name": 4, "r": 1.03264, "g": 28.3863, "b": 1.7638}
	]
},
{"uid": "P-147-71-3-7", "weight": 0.25, "r": 0, "g": 0, "b": 0, 
	"vertices": [
		{"obj_name": 1, "r": 86.8654, "g": 66.2242, "b": 161.292},
		{"obj_name": 4, "r": 98.9892, "g": 70.902, "b": 117.123},
		{"obj_name": 0, "r": 20.6198, "g": 0.00878851, "b": 111.508},
		{"obj_name": 4, "r": 1.02252, "g": 11.5388, "b": 141.993},
		{"obj_name": 5, "r": 8.02941, "g": 0.019458, "b": 127.753},
		{"obj_name": 1, "r": 79.9175, "g": 81.5952, "b": 89.395},
		{"obj_name": 5, "r": 98.9945, "g": 73.933, "b": 83.2055}
	]
}
]}