{"paths": [
{"uid": "P-146-48-2-0", "weight": 0.25, "r": 0, "g": 0, "b": 0, 
	"vertices": [
		{"obj_name": 1, "r": 85.834, "g": 49.1198, "b": 160.294},
		{"obj_name": 4, "r": 98.9955, "g": 48.0619, "b": 110.598},
		{"obj_name": 5, "r": 62.9226, "g": 0.00516072, "b": 111.013},
		{"obj_name": 4, "r": 91.4069, "g": 81.5525, "b": 169.85},
		{"obj_name": 5, "r": 34.9897, "g": 0.0204242, "b": 19.4748},
		{"obj_name": 4, "r": 85.3144, "g": 81.5937, "b": 84.6137},
		{"obj_name": 1, "r": 79.2662, "g": 0.0134406, "b": 38.8027},
		{"obj_name": 5, "r": 98.9642, "g": 11.7008, "b": 2.20416}
	]
},
{"uid": "P-146-48-2-1", "weight": 0.25, "r": 0, "g": 0, "b": 0, 
	"vertices": [
		{"obj_name": 1, "r": 85.4773, "g": 49.4067, "b": 160.195},
		{"obj_name": 0, "r": 98.9961, "g": 48.4186, "b": 108.598},
		{"obj_name": 1, "r": 1.00971, "g": 68.3537, "b": 116.002},
		{"obj_name": 0, "r": 98.9988, "g": 50.0606, "b": 94.0734},
		{"obj_name": 5, "r": 1.02021, "g": 80.0286, "b": 131.622},
		{"obj_name": 0, "r": 6.421, "g": 81.5802, "b": 127.025},
		{"obj_name": 7, "r": 1.01588, "g": 73.2454, "b": 127.69},
		{"obj_name": 1, "r": 72.5776, "g": 30.4813, "b": 86.7518},
		{"obj_name": 0, "r": 98.9983, "g": 53.0637, "b": 95.4228},
		{"obj_name": 4, "r": 1.00807, "g": 69.2669, "b": 109.932},
		{"obj_name": 5, "r": 75.572, "g": 0.0142164, "b": 128.39},
		{"obj_name": 3, "r": 84.2322, "g": 81.5613, "b": 162.656}
	]
},
{"uid": "P-146-48-2-2", "weight": 0.25, "r": 0, "g": 0, "b": 0, 
	"vertices": [
		{"obj_name": 1, "r": 85.5233, "g": 49.0483, "b": 160.214},
		{"obj_name": 4, "r": 98.996, "g": 47.9288, "b": 108.867},
		{"obj_name": 2, "r": 65.3415, "g": 0.0100426, "b": 123.709},
		{"obj_name": 3, "r": 34.959, "g": 63.5649, "b": 0.00372237},
		{"obj_name": 5, "r": 41.3279, "g": 51.7048, "b": 169.999},
		{"obj_name": 4, "r": 75.3368, "g": 81.5867, "b": 126.499},
		{"obj_name": 0, "r": 2.68441, "g": 0.0284436, "b": 140.336},
		{"obj_name": 4, "r": 1.02504, "g": 3.58262, "b": 141.785},
		{"obj_name": 0, "r": 9.41571, "g": 0.0249194, "b": 139.365},
		{"obj_name": 4, "r": 1.0175, "g": 7.1089, "b": 130.235},
		{"obj_name": 1, "r": 84.1027, "g": 0.011514, "b": 115.361},
		{"obj_name": 5, "r": 98.9954, "g": 24.2504, "b": 106.978},
		{"obj_name": 1, "r": 85.8358, "g": 81.5934, "b": 87.1953},
		{"obj_name": 2, "r": 98.9932, "g": 75.6848, "b": 69.9814}
	]
},
{"uid": "P-146-48-2-3", "weight": 0.25, "r": 0, "g": 0, "b": 0, 
	"vertices": [
		{"obj_name": 1, "r": 85.625, "g": 48.9271, "b": 160.243},
		{"obj_name": 3, "r": 98.9959, "g": 47.7738, "b": 109.441},
		{"obj_name": 0, "r": 5.18005, "g": 23.8621, "b": 169.989},
		{"obj_name": 3, "r": 1.033, "g": 21.6513, "b": 160.551},
		{"obj_name": 4, "r": 21.3569, "g": 25.0151, "b": 169.995},
		{"obj_name": 5, "r": 33.5997, "g": 0.0287046, "b": 155.573},
		{"obj_name": 0, "r": 24.9968, "g": 81.5712, "b": 153.322},
		{"obj_name": 5, "r": 1.00953, "g": 54.1266, "b": 123.176},
		{"obj_name": 7, "r": 76.096, "g": 81.5776, "b": 143.19},
		{"obj_name": 4, "r": 69.2051, "g": 14.8881, "b": 93.9766}
	]
},
{"uid": "P-146-48-2-4", "weight": 0.25, "r": 0, "g": 0, "b": 0, 
	"vertices": [
		{"obj_name": 1, "r": 85.6307, "g": 49.176, "b": 160.239},
		{"obj_name": 0, "r": 98.9958, "g": 48.1167, "b": 109.465},
		{"obj_name": 2, "r": 1.02596, "g": 49.3271, "b": 153.155},
		{"obj_name": 0, "r": 93.5045, "g": 60.3312, "b": 0.0113706},
		{"obj_name": 5, "r": 1.00064, "g": 49.0174, "b": 73.8039},
		{"obj_name": 2, "r": 28.4603, "g": 81.5967, "b": 67.666},
		{"obj_name": 6, "r": 21.9928, "g": 45.1934, "b": 0.00401852},
		{"obj_name": 1, "r": 36.4494, "g": 24.733, "b": 36.268},
		{"obj_name": 2, "r": 98.9912, "g": 31.8974, "b": 40.6637},
		{"obj_name": 1, "r": 72.1592, "g": 19.245, "b": 0.00477825},
		{"obj_name": 0, "r": 98.9723, "g": 34.4688, "b": 7.42046}
	]
},
{"uid": "P-146-48-2-5", "weight": 0.25, "r": 0, "g": 0, "b": 0, 
	"vertices": [
		{"obj_name": 1, "r": 85.5279, "g": 49.035, "b": 160.215},
		{"obj_name": 0, "r": 98.996, "g": 47.9111, "b": 108.893},
		{"obj_name": 2, "r": 1.00247, "g": 40.8849, "b": 103.842},
		{"obj_name": 0, "r": 7.14527, "g": 56.4505, "b": 0.0104073},
		{"obj_name": 2, "r": 1.03117, "g": 60.4041, "b": 5.11926},
		{"obj_name": 0, "r": 8.59797, "g": 52.4428, "b": 0.00924842}
	]
},
{"uid": "P-146-48-2-6", "weight": 0.25, "r": 0.0006, "g": 0.0006, "b": 0.0018, 
	"vertices": [
		{"obj_name": 1, "r": 85.742, "g": 48.9643, "b": 160.273},
		{"obj_name": 8, "r": 98.9957, "g": 47.8386, "b": 110.092},
		{"obj_name": 1, "r": 52.8025, "g": 81.3695, "b": 87.8915},
		{"obj_name": 0, "r": 98.9956, "g": 60.3651, "b": 103.924},
		{"obj_name": 4, "r": 1.01637, "g": 50.8785, "b": 137.916},
		{"obj_name": 5, "r": 14.7831, "g": 0.012796, "b": 117.918},
		{"obj_name": 3, "r": 14.1021, "g": 81.5895, "b": 109.918}
	]
},
{"uid": "P-146-48-2-7", "weight": 0.25, "r": 0, "g": 0, "b": 0, 
	"vertices": [
		{"obj_name": 1, "r": 86.0058, "g": 49.0408, "b": 160.342},
		{"obj_name": 5, "r": 98.9953, "g": 47.9732, "b": 111.546},
		{"obj_name": 0, "r": 42.2551, "g": 81.5919, "b": 42.1359},
		{"obj_name": 1, "r": 1.01585, "g": 34.3816, "b": 25.6557},
		{"obj_name": 6, "r": 98.9898, "g": 21.8093, "b": 40.4999},
		{"obj_name": 4, "r": 38.88, "g": 6.34245, "b": 41.7143},
		{"obj_name": 6, "r": 37.6755, "g": 0.00964725, "b": 39.4389},
		{"obj_name": 4, "r": 34.2817, "g": 3.65021, "b": 39.6441},
		{"obj_name": 5, "r": 34.8539, "g": 0.0117924, "b": 35.4582},
		{"obj_name": 4, "r": 64.5717, "g": 81.5762, "b": 14.1791},
		{"obj_name": 1, "r": 61.6934, "g": 0.0143972, "b": 29.2291}
	]
}
]}