{"paths": [
{"uid": "P-158-44-1-0", "weight": 0.25, "r": 0, "g": 0, "b": 0, 
	"vertices": [
		{"obj_name": 1, "r": 94.2224, "g": 45.8409, "b": 162.911},
		{"obj_name": 0, "r": 98.9774, "g": 45.1787, "b": 148.643},
		{"obj_name": 5, "r": 1.00312, "g": 65.6677, "b": 79.2219},
		{"obj_name": 4, "r": 27.3663, "g": 81.5974, "b": 83.2186},
		{"obj_name": 5, "r": 20.7119, "g": 0.00801146, "b": 108.886},
		{"obj_name": 4, "r": 2.58743, "g": 81.5853, "b": 107.761},
		{"obj_name": 5, "r": 8.53257, "g": 0.0151893, "b": 117.909},
		{"obj_name": 2, "r": 44.3225, "g": 81.5946, "b": 49.3034}
	]
},
{"uid": "P-158-44-1-1", "weight": 0.25, "r": 0, "g": 0, "b": 0, 
	"vertices": [
		{"obj_name": 1, "r": 94.5348, "g": 45.6387, "b": 163.025},
		{"obj_name": 5, "r": 98.9767, "g": 45.0043, "b": 149.802},
		{"obj_name": 4, "r": 58.4813, "g": 81.5846, "b": 136.364},
		{"obj_name": 0, "r": 20.2811, "g": 0.0338174, "b": 158.283},
		{"obj_name": 3, "r": 1.03086, "g": 5.91123, "b": 151.983},
		{"obj_name": 5, "r": 33.2051, "g": 34.061, "b": 169.998},
		{"obj_name": 0, "r": 6.84869, "g": 81.5856, "b": 49.7449},
		{"obj_name": 5, "r": 1.00293, "g": 64.692, "b": 77.7243}
	]
},
{"uid": "P-158-44-1-2", "weight": 0.25, "r": 0, "g": 0, "b": 0, 
	"vertices": [
		{"obj_name": 1, "r": 94.6124, "g": 45.7471, "b": 163.046},
		{"obj_name": 0, "r": 98.9765, "g": 45.1355, "b": 150.079},
		{"obj_name": 3, "r": 1.02616, "g": 37.774, "b": 153.873},
		{"obj_name": 0, "r": 62.0175, "g": 18.9442, "b": 169.997},
		{"obj_name": 3, "r": 1.0222, "g": 52.7128, "b": 147.156},
		{"obj_name": 2, "r": 31.8092, "g": 42.2122, "b": 169.998},
		{"obj_name": 1, "r": 90.0026, "g": 25.3687, "b": 0.00919166},
		{"obj_name": 2, "r": 98.9736, "g": 29.4955, "b": 9.78672},
		{"obj_name": 4, "r": 89.5306, "g": 31.9509, "b": 0.00820487},
		{"obj_name": 1, "r": 98.2193, "g": 0.0265883, "b": 136.304}
	]
},
{"uid": "P-158-44-1-3", "weight": 0.25, "r": 0, "g": 0, "b": 0, 
	"vertices": [
		{"obj_name": 1, "r": 94.6856, "g": 45.6646, "b": 163.074},
		{"obj_name": 5, "r": 98.9763, "g": 45.0562, "b": 150.349},
		{"obj_name": 0, "r": 41.5503, "g": 81.5663, "b": 163.218},
		{"obj_name": 4, "r": 1.01458, "g": 14.8152, "b": 128.944},
		{"obj_name": 0, "r": 15.884, "g": 0.0144347, "b": 123.109},
		{"obj_name": 5, "r": 1.00391, "g": 30.0269, "b": 107.397},
		{"obj_name": 3, "r": 8.98988, "g": 81.5853, "b": 117.038}
	]
},
{"uid": "P-158-44-1-4", "weight": 0.25, "r": 0, "g": 0, "b": 0, 
	"vertices": [
		{"obj_name": 1, "r": 94.4993, "g": 45.4666, "b": 163.021},
		{"obj_name": 3, "r": 98.9767, "g": 44.8092, "b": 149.681},
		{"obj_name": 1, "r": 80.8143, "g": 29.6145, "b": 169.995},
		{"obj_name": 5, "r": 98.9654, "g": 32.5438, "b": 164.333},
		{"obj_name": 4, "r": 23.6405, "g": 81.5958, "b": 69.4175},
		{"obj_name": 6, "r": 49.3451, "g": 0.00578879, "b": 47.5805},
		{"obj_name": 4, "r": 41.0759, "g": 8.48287, "b": 43.8626},
		{"obj_name": 2, "r": 88.8893, "g": 0.0365379, "b": 5.47372},
		{"obj_name": 1, "r": 90.6032, "g": 7.96215, "b": 0.0136347},
		{"obj_name": 2, "r": 98.9678, "g": 5.06665, "b": 9.71847},
		{"obj_name": 0, "r": 52.2972, "g": 41.4841, "b": 2.87256e-05},
		{"obj_name": 5, "r": 1.02195, "g": 39.1259, "b": 147.833}
	]
},
{"uid": "P-158-44-1-5", "weight": 0.25, "r": 0, "g": 0, "b": 0, 
	"vertices": [
		{"obj_name": 1, "r": 94.5766, "g": 45.8126, "b": 163.031},
		{"obj_name": 3, "r": 98.9765, "g": 45.2019, "b": 149.945},
		{"obj_name": 1, "r": 90.1988, "g": 53.4005, "b": 169.991},
		{"obj_name": 5, "r": 98.9647, "g": 77.1967, "b": 157.283},
		{"obj_name": 3, "r": 88.6481, "g": 81.5623, "b": 159.328},
		{"obj_name": 5, "r": 89.8832, "g": 70.7802, "b": 169.988},
		{"obj_name": 3, "r": 82.777, "g": 81.5732, "b": 147.088}
	]
},
{"uid": "P-158-44-1-6", "weight": 0.25, "r": 0, "g": 0, "b": 0, 
	"vertices": [
		{"obj_name": 1, "r": 94.596, "g": 45.7887, "b": 163.038},
		{"obj_name": 0, "r": 98.9765, "g": 45.1786, "b": 150.017},
		{"obj_name": 4, "r": 1.00154, "g": 23.5094, "b": 78.5823},
		{"obj_name": 2, "r": 12.2981, "g": 0.0170004, "b": 37.1179},
		{"obj_name": 0, "r": 15.0823, "g": 19.7662, "b": 0.00830834},
		{"obj_name": 6, "r": 1.01207, "g": 12.0573, "b": 41.7509},
		{"obj_name": 0, "r": 10.9755, "g": 13.7467, "b": 44.192},
		{"obj_name": 4, "r": 1.01154, "g": 12.0128, "b": 43.126},
		{"obj_name": 6, "r": 15.1261, "g": 0.014523, "b": 40.5096},
		{"obj_name": 2, "r": 19.8352, "g": 5.09143, "b": 37.4732},
		{"obj_name": 4, "r": 26.9339, "g": 4.17998, "b": 0.00936534},
		{"obj_name": 5, "r": 21.1988, "g": 0.0355435, "b": 2.3587},
		{"obj_name": 2, "r": 39.5438, "g": 81.5665, "b": 0.45842},
		{"obj_name": 5, "r": 39.3996, "g": 80.7695, "b": 0.00854964},
		{"obj_name": 6, "r": 40.2302, "g": 81.5672, "b": 1.19148},
		{"obj_name": 7, "r": 41.7919, "g": 23.7864, "b": 46.4016},
		{"obj_name": 7, "r": 64.884, "g": 6.84073, "b": 67.3662},
		{"obj_name": 7, "r": 82.9511, "g": 6.41045, "b": 86.4514},
		{"obj_name": 5, "r": 75.7666, "g": 31.5831, "b": 84.0906},
		{"obj_name": 6, "r": 38.7618, "g": 81.5959, "b": 55.2753},
		{"obj_name": 0, "r": 17.5959, "g": 28.8502, "b": 52.5934},
		{"obj_name": 4, "r": 1.004, "g": 25.6401, "b": 57.7219},
		{"obj_name": 7, "r": 68.5635, "g": 0.00179547, "b": 85.4068},
		{"obj_name": 7, "r": 68.263, "g": 1.80914, "b": 83.83},
		{"obj_name": 5, "r": 68.9599, "g": 27.4197, "b": 66.3086},
		{"obj_name": 1, "r": 79.4048, "g": 81.5862, "b": 37.9806},
		{"obj_name": 5, "r": 98.986, "g": 78.2046, "b": 44.1833}
	]
},
{"uid": "P-158-44-1-7", "weight": 0.25, "r": 0.0003375, "g": 0.0001125, "b": 0.0003375, 
	"vertices": [
		{"obj_name": 1, "r": 94.2923, "g": 46.0781, "b": 162.923},
		{"obj_name": 0, "r": 98.9773, "g": 45.4517, "b": 148.889},
		{"obj_name": 4, "r": 1.00892, "g": 61.4625, "b": 118.445},
		{"obj_name": 8, "r": 44.6615, "g": 0.0116902, "b": 129.658},
		{"obj_name": 6, "r": 42.8819, "g": 81.3771, "b": 79.1803},
		{"obj_name": 7, "r": 37.2982, "g": 24.5032, "b": 57.1067},
		{"obj_name": 6, "r": 58.3383, "g": 18.7824, "b": 70.7838},
		{"obj_name": 0, "r": 33.185, "g": 20.1588, "b": 61.8529},
		{"obj_name": 1, "r": 1.00718, "g": 43.6976, "b": 119.387},
		{"obj_name": 4, "r": 98.9744, "g": 28.3136, "b": 152.068}
	]
}
]}