{"paths": [
{"uid": "P-198-28-1-0", "weight": 0.25, "r": 0, "g": 0, "b": 0, 
	"vertices": [
		{"obj_name": 3, "r": 118.339, "g": 35.18, "b": 174.576},
		{"obj_name": 5, "r": 120.937, "g": 34.5406, "b": 169.975},
		{"obj_name": 4, "r": 158.674, "g": 81.4276, "b": 232.133},
		{"obj_name": 5, "r": 103.563, "g": 0.272809, "b": 308.961},
		{"obj_name": 4, "r": 160.94, "g": 81.0996, "b": 377.879},
		{"obj_name": 5, "r": 164.552, "g": 0.318301, "b": 306.406},
		{"obj_name": 4, "r": 653.895, "g": 79.5745, "b": 282.63}
	]
},
{"uid": "P-198-28-1-1", "weight": 0.25, "r": 0, "g": 0, "b": 0, 
	"vertices": [
		{"obj_name": 3, "r": 118.667, "g": 35.4226, "b": 174.728},
		{"obj_name": 5, "r": 121.367, "g": 34.7707, "b": 169.974},
		{"obj_name": 4, "r": 690.422, "g": 78.7164, "b": 489.724},
		{"obj_name": 5, "r": 558.572, "g": 2.05345, "b": 471.524},
		{"obj_name": 4, "r": 634.692, "g": 79.5647, "b": 336.927},
		{"obj_name": 5, "r": 642.278, "g": 2.37147, "b": 433.018},
		{"obj_name": 4, "r": 787.078, "g": 78.5803, "b": 327.848},
		{"obj_name": 5, "r": 771.263, "g": 2.67966, "b": 206.915}
	]
},
{"uid": "P-198-28-1-2", "weight": 0.25, "r": 0, "g": 0, "b": 0, 
	"vertices": [
		{"obj_name": 3, "r": 118.619, "g": 35.4107, "b": 174.702},
		{"obj_name": 1, "r": 121.302, "g": 34.7619, "b": 169.974},
		{"obj_name": 3, "r": 98.9085, "g": 81.1575, "b": 210.684},
		{"obj_name": 4, "r": 513.501, "g": 72.1975, "b": 168.921},
		{"obj_name": 5, "r": 331.75, "g": 0.855675, "b": 384.505},
		{"obj_name": 4, "r": 321.218, "g": 80.7741, "b": 384.282},
		{"obj_name": 5, "r": 343.625, "g": 0.825536, "b": 362.475}
	]
},
{"uid": "P-198-28-1-3", "weight": 0.25, "r": 0, "g": 0, "b": 0, 
	"vertices": [
		{"obj_name": 3, "r": 118.479, "g": 35.027, "b": 174.676},
		{"obj_name": 4, "r": 121.142, "g": 34.367, "b": 169.974},
		{"obj_name": 5, "r": 126.801, "g": 0.102229, "b": 202.213},
		{"obj_name": 3, "r": 144.57, "g": 81.4894, "b": 196.403},
		{"obj_name": 5, "r": 144.804, "g": 29.7098, "b": 169.954},
		{"obj_name": 4, "r": 298.383, "g": 80.5858, "b": 457.292},
		{"obj_name": 5, "r": 320.948, "g": 0.786012, "b": 371.063},
		{"obj_name": 4, "r": 367.353, "g": 80.9755, "b": 237.117},
		{"obj_name": 5, "r": 393.274, "g": 0.672624, "b": 210.779},
		{"obj_name": 4, "r": 409.241, "g": 80.8319, "b": 238.331},
		{"obj_name": 5, "r": 386.456, "g": 0.649132, "b": 210.53}
	]
},
{"uid": "P-198-28-1-4", "weight": 0.25, "r": 0, "g": 0, "b": 0, 
	"vertices": [
		{"obj_name": 3, "r": 118.393, "g": 35.3913, "b": 174.577},
		{"obj_name": 1, "r": 120.994, "g": 34.7597, "b": 169.975},
		{"obj_name": 3, "r": 98.854, "g": 10.9829, "b": 249.887},
		{"obj_name": 4, "r": 239.851, "g": 32.1356, "b": 169.819},
		{"obj_name": 5, "r": 361.067, "g": 0.564028, "b": 208.26},
		{"obj_name": 4, "r": 399.789, "g": 80.932, "b": 187.681},
		{"obj_name": 5, "r": 409.108, "g": 0.765273, "b": 236.828},
		{"obj_name": 4, "r": 725.203, "g": 78.7526, "b": 418.593}
	]
},
{"uid": "P-198-28-1-5", "weight": 0.25, "r": 0, "g": 0, "b": 0, 
	"vertices": [
		{"obj_name": 3, "r": 118.464, "g": 35.4763, "b": 174.606},
		{"obj_name": 4, "r": 121.084, "g": 34.8438, "b": 169.975},
		{"obj_name": 1, "r": 155.229, "g": 0.171489, "b": 233.996},
		{"obj_name": 4, "r": 98.7956, "g": 57.2533, "b": 283.141},
		{"obj_name": 5, "r": 128.344, "g": 0.355558, "b": 336.499},
		{"obj_name": 4, "r": 229.189, "g": 81.2144, "b": 293.757}
	]
},
{"uid": "P-198-28-1-6", "weight": 0.25, "r": 0, "g": 0, "b": 0, 
	"vertices": [
		{"obj_name": 3, "r": 118.354, "g": 35.1964, "b": 174.582},
		{"obj_name": 4, "r": 120.956, "g": 34.5567, "b": 169.975},
		{"obj_name": 5, "r": 257.048, "g": 0.805597, "b": 425.475},
		{"obj_name": 4, "r": 350.716, "g": 80.974, "b": 268.051},
		{"obj_name": 5, "r": 310.185, "g": 0.780928, "b": 379.07},
		{"obj_name": 4, "r": 294.16, "g": 80.843, "b": 384.561},
		{"obj_name": 5, "r": 287.068, "g": 0.778458, "b": 397.02},
		{"obj_name": 4, "r": 295.615, "g": 80.9167, "b": 357.891},
		{"obj_name": 5, "r": 341.89, "g": 0.725929, "b": 326.519},
		{"obj_name": 4, "r": 335.628, "g": 80.4223, "b": 473.965},
		{"obj_name": 5, "r": 416.361, "g": 1.00563, "b": 340.26},
		{"obj_name": 4, "r": 402.501, "g": 80.7361, "b": 301.878}
	]
},
{"uid": "P-198-28-1-7", "weight": 0.25, "r": 0, "g": 0, "b": 0, 
	"vertices": [
		{"obj_name": 3, "r": 118.307, "g": 35.5391, "b": 174.508},
		{"obj_name": 4, "r": 120.865, "g": 34.9228, "b": 169.975},
		{"obj_name": 3, "r": 168.936, "g": 0.341787, "b": 314.434},
		{"obj_name": 5, "r": 263.214, "g": 53.5405, "b": 169.772},
		{"obj_name": 4, "r": 254.482, "g": 81.3445, "b": 177.934},
		{"obj_name": 3, "r": 305.154, "g": 0.377307, "b": 183.371}
	]
}
]}