{"paths": [
{"uid": "P-44-3-2-0", "weight": 0.25, "r": 0, "g": 0, "b": 0, 
	"vertices": [
		{"obj_name": 0, "r": 8.5728, "g": 15.7976, "b": 166.863},
		{"obj_name": 5, "r": 1.02409, "g": 9.20098, "b": 143.405},
		{"obj_name": 1, "r": 59.6903, "g": 81.5874, "b": 32.3339},
		{"obj_name": 0, "r": 98.9928, "g": 5.28632, "b": 94.6224},
		{"obj_name": 3, "r": 1.02996, "g": 13.8828, "b": 154.174},
		{"obj_name": 4, "r": 15.5871, "g": 3.63087, "b": 169.987},
		{"obj_name": 3, "r": 16.7979, "g": 0.0421726, "b": 167.228}
	]
},
{"uid": "P-44-3-2-1", "weight": 0.25, "r": 0, "g": 0, "b": 0, 
	"vertices": [
		{"obj_name": 0, "r": 8.82955, "g": 16.0013, "b": 166.724},
		{"obj_name": 3, "r": 1.02342, "g": 9.17573, "b": 142.288},
		{"obj_name": 4, "r": 29.0634, "g": 6.82922, "b": 169.992},
		{"obj_name": 1, "r": 29.4135, "g": 0.0358589, "b": 163.746},
		{"obj_name": 0, "r": 98.9945, "g": 73.9841, "b": 82.9937},
		{"obj_name": 1, "r": 1.00133, "g": 39.0206, "b": 97.7885},
		{"obj_name": 0, "r": 98.9923, "g": 59.5017, "b": 116.145},
		{"obj_name": 1, "r": 1.02251, "g": 1.85751, "b": 136.244},
		{"obj_name": 0, "r": 98.9685, "g": 34.4472, "b": 160.691},
		{"obj_name": 5, "r": 1.00093, "g": 36.6387, "b": 94.5904},
		{"obj_name": 4, "r": 60.2982, "g": 81.5947, "b": 112.58},
		{"obj_name": 5, "r": 10.4409, "g": 0.0379514, "b": 159.223}
	]
},
{"uid": "P-44-3-2-2", "weight": 0.25, "r": 0, "g": 0, "b": 0, 
	"vertices": [
		{"obj_name": 0, "r": 8.86499, "g": 15.9242, "b": 166.734},
		{"obj_name": 4, "r": 1.02338, "g": 9.04699, "b": 142.168},
		{"obj_name": 0, "r": 5.7909, "g": 0.0266674, "b": 139.729},
		{"obj_name": 5, "r": 1.01181, "g": 6.2962, "b": 115.825},
		{"obj_name": 4, "r": 70.6263, "g": 81.5942, "b": 108.64},
		{"obj_name": 1, "r": 95.4295, "g": 0.0151013, "b": 50.6739}
	]
},
{"uid": "P-44-3-2-3", "weight": 0.25, "r": 0, "g": 0, "b": 0, 
	"vertices": [
		{"obj_name": 0, "r": 8.69086, "g": 16.0228, "b": 166.762},
		{"obj_name": 1, "r": 1.0237, "g": 9.34528, "b": 142.849},
		{"obj_name": 5, "r": 98.994, "g": 75.3147, "b": 83.9655},
		{"obj_name": 4, "r": 96.5314, "g": 81.589, "b": 87.8338},
		{"obj_name": 5, "r": 62.2309, "g": 0.00229448, "b": 99.187},
		{"obj_name": 0, "r": 11.7439, "g": 81.5897, "b": 57.3206},
		{"obj_name": 1, "r": 1.01993, "g": 68.0652, "b": 24.6548},
		{"obj_name": 0, "r": 98.9946, "g": 24.5133, "b": 52.8862},
		{"obj_name": 4, "r": 1.00036, "g": 49.1895, "b": 80.1057}
	]
},
{"uid": "P-44-3-2-4", "weight": 0.25, "r": 0, "g": 0, "b": 0, 
	"vertices": [
		{"obj_name": 0, "r": 8.60315, "g": 15.719, "b": 166.876},
		{"obj_name": 3, "r": 1.02407, "g": 9.07652, "b": 143.308},
		{"obj_name": 0, "r": 16.1392, "g": 51.6206, "b": 169.994},
		{"obj_name": 3, "r": 1.02367, "g": 47.2026, "b": 150.107},
		{"obj_name": 0, "r": 17.7033, "g": 31.8849, "b": 169.994},
		{"obj_name": 4, "r": 1.0369, "g": 48.1384, "b": 167.188},
		{"obj_name": 5, "r": 64.0605, "g": 0.0216364, "b": 145.862}
	]
},
{"uid": "P-44-3-2-5", "weight": 0.25, "r": 0, "g": 0, "b": 0, 
	"vertices": [
		{"obj_name": 0, "r": 8.59277, "g": 15.7555, "b": 166.869},
		{"obj_name": 3, "r": 1.02407, "g": 9.13043, "b": 143.338},
		{"obj_name": 2, "r": 36.2901, "g": 35.9152, "b": 169.999},
		{"obj_name": 5, "r": 78.0148, "g": 63.2464, "b": 0.00644336},
		{"obj_name": 2, "r": 74.1602, "g": 81.5683, "b": 5.66628},
		{"obj_name": 1, "r": 83.3998, "g": 59.0782, "b": 0.00724821},
		{"obj_name": 5, "r": 98.9806, "g": 41.1723, "b": 19.3725}
	]
},
{"uid": "P-44-3-2-6", "weight": 0.25, "r": 0, "g": 0, "b": 0, 
	"vertices": [
		{"obj_name": 0, "r": 8.54801, "g": 16.0358, "b": 166.804},
		{"obj_name": 4, "r": 1.02401, "g": 9.50788, "b": 143.427},
		{"obj_name": 5, "r": 8.08736, "g": 0.0263669, "b": 140.902},
		{"obj_name": 4, "r": 1.56091, "g": 81.5837, "b": 111.747},
		{"obj_name": 5, "r": 6.80336, "g": 0.0116705, "b": 103.237},
		{"obj_name": 1, "r": 68.5935, "g": 81.5684, "b": 158.874},
		{"obj_name": 7, "r": 98.9943, "g": 73.5707, "b": 89.2533},
		{"obj_name": 7, "r": 68.4509, "g": 32.1495, "b": 75.4215},
		{"obj_name": 4, "r": 61.5436, "g": 5.87651, "b": 72.6951},
		{"obj_name": 0, "r": 62.1849, "g": 0.00109972, "b": 73.1458},
		{"obj_name": 1, "r": 1.00406, "g": 68.0494, "b": 89.8872}
	]
},
{"uid": "P-44-3-2-7", "weight": 0.25, "r": 0, "g": 0, "b": 0, 
	"vertices": [
		{"obj_name": 0, "r": 9.25882, "g": 15.724, "b": 166.665},
		{"obj_name": 4, "r": 1.02266, "g": 8.39052, "b": 140.6},
		{"obj_name": 5, "r": 20.7819, "g": 0.00987759, "b": 115.094},
		{"obj_name": 0, "r": 45.4546, "g": 81.5883, "b": 33.4644},
		{"obj_name": 2, "r": 1.02958, "g": 53.8398, "b": 5.7923},
		{"obj_name": 0, "r": 2.35466, "g": 59.415, "b": 0.013083}
	]
}
]}