{"paths": [
{"uid": "P-56-47-1-0", "weight": 0.25, "r": 0, "g": 0, "b": 0, 
	"vertices": [
		{"obj_name": 0, "r": 16.4719, "g": 48.0434, "b": 159.732},
		{"obj_name": 3, "r": 1.00134, "g": 46.2178, "b": 97.0392},
		{"obj_name": 5, "r": 47.9663, "g": 17.9553, "b": 169.997},
		{"obj_name": 0, "r": 21.5263, "g": 81.5841, "b": 32.9285},
		{"obj_name": 4, "r": 1.00227, "g": 32.2227, "b": 101.083},
		{"obj_name": 5, "r": 34.0735, "g": 0.0048496, "b": 108.363},
		{"obj_name": 1, "r": 22.0192, "g": 81.5759, "b": 17.9903},
		{"obj_name": 5, "r": 98.9801, "g": 78.8927, "b": 31.2294}
	]
},
{"uid": "P-56-47-1-1", "weight": 0.25, "r": 0, "g": 0, "b": 0, 
	"vertices": [
		{"obj_name": 0, "r": 16.592, "g": 47.8005, "b": 159.709},
		{"obj_name": 4, "r": 1.00121, "g": 45.8407, "b": 96.292},
		{"obj_name": 0, "r": 6.93981, "g": 0.0215831, "b": 131.223},
		{"obj_name": 4, "r": 1.01652, "g": 6.05556, "b": 127.393},
		{"obj_name": 0, "r": 10.1757, "g": 0.0191555, "b": 128.983},
		{"obj_name": 5, "r": 1.01283, "g": 14.2272, "b": 124.733},
		{"obj_name": 4, "r": 17.9601, "g": 81.5652, "b": 158.669},
		{"obj_name": 1, "r": 77.763, "g": 0.0388796, "b": 165.297},
		{"obj_name": 4, "r": 98.9661, "g": 3.95989, "b": 155.202}
	]
},
{"uid": "P-56-47-1-2", "weight": 0.25, "r": 0, "g": 0, "b": 0, 
	"vertices": [
		{"obj_name": 0, "r": 16.5553, "g": 48.1565, "b": 159.708},
		{"obj_name": 4, "r": 1.00127, "g": 46.3689, "b": 96.5088},
		{"obj_name": 5, "r": 95.1479, "g": 0.0377191, "b": 155.799},
		{"obj_name": 3, "r": 72.7443, "g": 81.5951, "b": 103.291},
		{"obj_name": 0, "r": 81.1666, "g": 23.6932, "b": 169.994},
		{"obj_name": 4, "r": 1.00666, "g": 35.1903, "b": 45.5409},
		{"obj_name": 0, "r": 19.8854, "g": 0.00454572, "b": 83.1013},
		{"obj_name": 5, "r": 1.00707, "g": 63.4165, "b": 111.65},
		{"obj_name": 2, "r": 29.3339, "g": 81.5942, "b": 108.667},
		{"obj_name": 5, "r": 66.6963, "g": 52.9605, "b": 0.00213322},
		{"obj_name": 4, "r": 14.176, "g": 81.5837, "b": 37.1456}
	]
},
{"uid": "P-56-47-1-3", "weight": 0.25, "r": 0, "g": 0, "b": 0, 
	"vertices": [
		{"obj_name": 0, "r": 16.3837, "g": 47.9799, "b": 159.755},
		{"obj_name": 7, "r": 1.00142, "g": 46.1404, "b": 97.5952},
		{"obj_name": 7, "r": 59.52, "g": 13.6625, "b": 68.9177},
		{"obj_name": 1, "r": 84.8196, "g": 8.38099, "b": 69.8373},
		{"obj_name": 5, "r": 98.9951, "g": 9.87667, "b": 77.1256},
		{"obj_name": 7, "r": 49.9411, "g": 81.5979, "b": 102.319},
		{"obj_name": 7, "r": 64.3111, "g": 21.6086, "b": 91.0635},
		{"obj_name": 4, "r": 75.1835, "g": 0.147133, "b": 77.743},
		{"obj_name": 7, "r": 75.332, "g": 0.00329134, "b": 77.531},
		{"obj_name": 7, "r": 75.2529, "g": 0.166565, "b": 77.3729},
		{"obj_name": 5, "r": 67.2755, "g": 25.1383, "b": 65.1603},
		{"obj_name": 4, "r": 55.7637, "g": 81.5967, "b": 56.5064},
		{"obj_name": 4, "r": 59.52, "g": 13.6625, "b": 68.9177},
		{"obj_name": 5, "r": 64.5532, "g": 0.00607215, "b": 49.9356},
		{"obj_name": 0, "r": 32.3871, "g": 81.5971, "b": 97.7181},
		{"obj_name": 5, "r": 1.00428, "g": 69.2799, "b": 88.2468},
		{"obj_name": 0, "r": 3.77851, "g": 81.589, "b": 89.0446},
		{"obj_name": 5, "r": 1.00758, "g": 75.4585, "b": 99.3656},
		{"obj_name": 0, "r": 12.3237, "g": 81.5904, "b": 103.756},
		{"obj_name": 3, "r": 1.00771, "g": 56.0461, "b": 117.775}
	]
},
{"uid": "P-56-47-1-4", "weight": 0.25, "r": 0, "g": 0, "b": 0, 
	"vertices": [
		{"obj_name": 0, "r": 16.5772, "g": 48.0977, "b": 159.704},
		{"obj_name": 5, "r": 1.00124, "g": 46.2791, "b": 96.3728},
		{"obj_name": 3, "r": 81.0046, "g": 81.5909, "b": 110.917},
		{"obj_name": 4, "r": 79.2276, "g": 5.67277, "b": 169.99},
		{"obj_name": 3, "r": 79.3863, "g": 0.0401542, "b": 166.26},
		{"obj_name": 0, "r": 75.2687, "g": 7.57573, "b": 169.991},
		{"obj_name": 1, "r": 1.02464, "g": 42.6155, "b": 151.776},
		{"obj_name": 2, "r": 98.9953, "g": 40.5969, "b": 51.0861},
		{"obj_name": 4, "r": 26.0321, "g": 20.5224, "b": 0.00492821}
	]
},
{"uid": "P-56-47-1-5", "weight": 0.25, "r": 0, "g": 0, "b": 0, 
	"vertices": [
		{"obj_name": 0, "r": 16.3298, "g": 47.8552, "b": 159.772},
		{"obj_name": 1, "r": 1.00147, "g": 45.9683, "b": 97.9367},
		{"obj_name": 7, "r": 98.9965, "g": 46.9732, "b": 107.375},
		{"obj_name": 7, "r": 84.5184, "g": 22.4427, "b": 88.2108},
		{"obj_name": 4, "r": 67.7801, "g": 3.35863, "b": 69.4966},
		{"obj_name": 7, "r": 63.4047, "g": 0.00224156, "b": 65.2102},
		{"obj_name": 7, "r": 64.6042, "g": 4.5094, "b": 70.3852},
		{"obj_name": 1, "r": 73.9621, "g": 26.3189, "b": 91.2255},
		{"obj_name": 3, "r": 98.9863, "g": 69.7615, "b": 125.191}
	]
},
{"uid": "P-56-47-1-6", "weight": 0.25, "r": 0, "g": 0, "b": 0, 
	"vertices": [
		{"obj_name": 0, "r": 16.4286, "g": 48.0018, "b": 159.744},
		{"obj_name": 4, "r": 1.00138, "g": 46.1644, "b": 97.3131},
		{"obj_name": 6, "r": 67.2881, "g": 0.0401118, "b": 169.483},
		{"obj_name": 4, "r": 37.041, "g": 12.4625, "b": 59.455},
		{"obj_name": 6, "r": 68.2372, "g": 0.00189302, "b": 74.817},
		{"obj_name": 5, "r": 41.0748, "g": 18.7588, "b": 55.3095}
	]
},
{"uid": "P-56-47-1-7", "weight": 0.25, "r": 0, "g": 0, "b": 0, 
	"vertices": [
		{"obj_name": 0, "r": 16.055, "g": 48.526, "b": 159.822},
		{"obj_name": 5, "r": 1.00181, "g": 46.9855, "b": 99.6103},
		{"obj_name": 4, "r": 26.0564, "g": 81.59, "b": 119.422},
		{"obj_name": 0, "r": 6.90425, "g": 0.0130113, "b": 108.895},
		{"obj_name": 2, "r": 1.01121, "g": 1.06306, "b": 107.345},
		{"obj_name": 5, "r": 82.5056, "g": 49.2771, "b": 0.00564238},
		{"obj_name": 1, "r": 88.4702, "g": 81.5661, "b": 8.78865},
		{"obj_name": 5, "r": 98.963, "g": 79.4829, "b": 4.75785},
		{"obj_name": 2, "r": 98.5065, "g": 81.5582, "b": 4.05252},
		{"obj_name": 1, "r": 95.8938, "g": 77.553, "b": 0.0172851},
		{"obj_name": 2, "r": 98.9623, "g": 78.1599, "b": 3.26666}
	]
}
]}