{"paths": [
{"uid": "P-66-3-2-0", "weight": 0.25, "r": 0, "g": 0, "b": 0, 
	"vertices": [
		{"obj_name": 4, "r": 24.3781, "g": 14.9695, "b": 163.04},
		{"obj_name": 5, "r": 14.0278, "g": 0.0103592, "b": 109.49},
		{"obj_name": 1, "r": 85.2515, "g": 81.567, "b": 154.805},
		{"obj_name": 0, "r": 98.9856, "g": 32.4262, "b": 134.529},
		{"obj_name": 2, "r": 1.00925, "g": 24.9638, "b": 121.597},
		{"obj_name": 1, "r": 89.6557, "g": 23.3443, "b": 0.00938636},
		{"obj_name": 5, "r": 98.9805, "g": 30.5732, "b": 20.0287},
		{"obj_name": 4, "r": 56.2241, "g": 81.5967, "b": 56.5136},
		{"obj_name": 5, "r": 83.6608, "g": 0.0161047, "b": 127.293},
		{"obj_name": 1, "r": 45.3237, "g": 81.5921, "b": 42.0807}
	]
},
{"uid": "P-66-3-2-1", "weight": 0.25, "r": 0, "g": 0, "b": 0, 
	"vertices": [
		{"obj_name": 4, "r": 24.1742, "g": 14.9922, "b": 163.073},
		{"obj_name": 5, "r": 13.7192, "g": 0.0104519, "b": 109.422},
		{"obj_name": 4, "r": 91.2855, "g": 81.5912, "b": 89.1865},
		{"obj_name": 5, "r": 41.7579, "g": 0.0231461, "b": 14.0628},
		{"obj_name": 1, "r": 92.0669, "g": 81.5609, "b": 3.75958},
		{"obj_name": 0, "r": 98.9677, "g": 71.2248, "b": 7.16144},
		{"obj_name": 6, "r": 1.0206, "g": 33.9575, "b": 17.7736},
		{"obj_name": 2, "r": 21.858, "g": 21.841, "b": 32.2594},
		{"obj_name": 1, "r": 29.2922, "g": 25.3978, "b": 0.00333021},
		{"obj_name": 7, "r": 98.9887, "g": 50.2243, "b": 35.1074},
		{"obj_name": 7, "r": 76.6721, "g": 28.6996, "b": 67.515},
		{"obj_name": 4, "r": 63.5918, "g": 10.2083, "b": 90.0063}
	]
},
{"uid": "P-66-3-2-2", "weight": 0.25, "r": 0, "g": 0, "b": 0, 
	"vertices": [
		{"obj_name": 4, "r": 24.2015, "g": 14.8602, "b": 163.104},
		{"obj_name": 3, "r": 13.8865, "g": 0.0105904, "b": 110.129},
		{"obj_name": 5, "r": 55.9668, "g": 66.9452, "b": 169.996},
		{"obj_name": 3, "r": 17.0751, "g": 81.5599, "b": 164.866},
		{"obj_name": 0, "r": 6.85023, "g": 68.8869, "b": 169.987},
		{"obj_name": 5, "r": 1.02245, "g": 51.5032, "b": 147.752},
		{"obj_name": 3, "r": 40, "g": 81.5751, "b": 151.438}
	]
},
{"uid": "P-66-3-2-3", "weight": 0.25, "r": 0, "g": 0, "b": 0, 
	"vertices": [
		{"obj_name": 4, "r": 24.4803, "g": 14.7868, "b": 163.071},
		{"obj_name": 5, "r": 14.3471, "g": 0.0105165, "b": 110.447},
		{"obj_name": 1, "r": 63.717, "g": 81.588, "b": 128.674},
		{"obj_name": 3, "r": 98.9714, "g": 25.4335, "b": 155.674},
		{"obj_name": 4, "r": 75.5272, "g": 22.2838, "b": 169.995},
		{"obj_name": 1, "r": 79.3862, "g": 0.0188567, "b": 135.524}
	]
},
{"uid": "P-66-3-2-4", "weight": 0.25, "r": 0, "g": 0, "b": 0, 
	"vertices": [
		{"obj_name": 4, "r": 24.1211, "g": 14.8533, "b": 163.122},
		{"obj_name": 0, "r": 13.7808, "g": 0.0106456, "b": 110.188},
		{"obj_name": 4, "r": 1.01014, "g": 3.48002, "b": 106.815},
		{"obj_name": 2, "r": 7.66948, "g": 0.0103784, "b": 98.4467},
		{"obj_name": 1, "r": 18.5998, "g": 64.6309, "b": 0.00776942},
		{"obj_name": 7, "r": 98.9983, "g": 30.6823, "b": 65.8904},
		{"obj_name": 4, "r": 84.4807, "g": 14.5018, "b": 66.3188},
		{"obj_name": 2, "r": 82.2816, "g": 0.0081994, "b": 57.1505}
	]
},
{"uid": "P-66-3-2-5", "weight": 0.25, "r": 0, "g": 0, "b": 0, 
	"vertices": [
		{"obj_name": 4, "r": 24.3384, "g": 14.5465, "b": 163.166},
		{"obj_name": 5, "r": 14.3792, "g": 0.0108951, "b": 111.769},
		{"obj_name": 0, "r": 7.88888, "g": 81.5635, "b": 155.876},
		{"obj_name": 1, "r": 1.03539, "g": 76.5516, "b": 157.754},
		{"obj_name": 5, "r": 98.9902, "g": 65.1963, "b": 118.488},
		{"obj_name": 2, "r": 85.9092, "g": 81.5835, "b": 126.506},
		{"obj_name": 7, "r": 79.8145, "g": 0.805351, "b": 0.0124424},
		{"obj_name": 7, "r": 68.215, "g": 11.7972, "b": 62.9256},
		{"obj_name": 3, "r": 67.7661, "g": 18.5607, "b": 93.5116}
	]
},
{"uid": "P-66-3-2-6", "weight": 0.25, "r": 0, "g": 0, "b": 0, 
	"vertices": [
		{"obj_name": 4, "r": 24.3564, "g": 14.6392, "b": 163.137},
		{"obj_name": 5, "r": 14.3158, "g": 0.0107687, "b": 111.271},
		{"obj_name": 1, "r": 87.6833, "g": 81.5899, "b": 57.0107},
		{"obj_name": 0, "r": 98.992, "g": 66.0672, "b": 50.7287},
		{"obj_name": 3, "r": 1.00185, "g": 35.4141, "b": 63.1428},
		{"obj_name": 5, "r": 55.0521, "g": 26.4975, "b": 169.999}
	]
},
{"uid": "P-66-3-2-7", "weight": 0.25, "r": 0, "g": 0, "b": 0, 
	"vertices": [
		{"obj_name": 4, "r": 24.6322, "g": 14.6123, "b": 163.091},
		{"obj_name": 5, "r": 14.7249, "g": 0.0106441, "b": 111.34},
		{"obj_name": 4, "r": 74.0033, "g": 81.59, "b": 119.255},
		{"obj_name": 0, "r": 90.0202, "g": 0.0161792, "b": 122.026},
		{"obj_name": 4, "r": 1.00064, "g": 41.3224, "b": 70.3237},
		{"obj_name": 0, "r": 50.5214, "g": 3.42412e-06, "b": 80.9574}
	]
}
]}