{"paths": [
{"uid": "P-85-4-0-0", "weight": 0.25, "r": 0, "g": 0, "b": 0, 
	"vertices": [
		{"obj_name": 4, "r": 38.4277, "g": 14.9032, "b": 161.101},
		{"obj_name": 0, "r": 33.7801, "g": 0.00456274, "b": 107.085},
		{"obj_name": 2, "r": 1.01724, "g": 2.28199, "b": 125.932},
		{"obj_name": 4, "r": 97.1195, "g": 33.1722, "b": 0.0113922},
		{"obj_name": 3, "r": 64.4899, "g": 0.0134334, "b": 31.8333},
		{"obj_name": 1, "r": 37.5089, "g": 34.803, "b": 169.999},
		{"obj_name": 3, "r": 98.9846, "g": 36.8973, "b": 136.981}
	]
},
{"uid": "P-85-4-0-1", "weight": 0.25, "r": 0, "g": 0, "b": 0, 
	"vertices": [
		{"obj_name": 4, "r": 38.6222, "g": 14.6299, "b": 161.16},
		{"obj_name": 5, "r": 34.1694, "g": 0.00488366, "b": 108.547},
		{"obj_name": 4, "r": 51.3229, "g": 81.595, "b": 113.182},
		{"obj_name": 7, "r": 56.3953, "g": 0.000324123, "b": 76.7088},
		{"obj_name": 7, "r": 61.2726, "g": 6.36551, "b": 72.3422},
		{"obj_name": 1, "r": 80.0728, "g": 27.0685, "b": 67.4865},
		{"obj_name": 2, "r": 98.9994, "g": 45.0343, "b": 71.5868},
		{"obj_name": 1, "r": 62.9271, "g": 80.1942, "b": 0.00859508}
	]
},
{"uid": "P-85-4-0-2", "weight": 0.25, "r": 0, "g": 0, "b": 0, 
	"vertices": [
		{"obj_name": 4, "r": 38.3218, "g": 14.73, "b": 161.158},
		{"obj_name": 0, "r": 33.7078, "g": 0.00482289, "b": 108.041},
		{"obj_name": 5, "r": 1.0157, "g": 55.0405, "b": 27.4131},
		{"obj_name": 2, "r": 33.3531, "g": 81.5801, "b": 20.7338},
		{"obj_name": 5, "r": 80.8642, "g": 42.8937, "b": 0.00478491},
		{"obj_name": 2, "r": 77.7305, "g": 81.576, "b": 18.1005},
		{"obj_name": 0, "r": 74.4147, "g": 76.0853, "b": 0.00920566},
		{"obj_name": 5, "r": 1.00932, "g": 68.5856, "b": 114.644},
		{"obj_name": 2, "r": 11.2592, "g": 81.5872, "b": 114.099},
		{"obj_name": 0, "r": 38.6373, "g": 34.0579, "b": 0.000872839}
	]
},
{"uid": "P-85-4-0-3", "weight": 0.25, "r": 0, "g": 0, "b": 0, 
	"vertices": [
		{"obj_name": 4, "r": 38.759, "g": 14.9016, "b": 161.074},
		{"obj_name": 3, "r": 34.245, "g": 0.00448047, "b": 107.053},
		{"obj_name": 7, "r": 47.8097, "g": 32.1034, "b": 170},
		{"obj_name": 7, "r": 67.759, "g": 18.3578, "b": 93.5348},
		{"obj_name": 2, "r": 76.7178, "g": 13.355, "b": 62.2349},
		{"obj_name": 4, "r": 96.1134, "g": 4.65945, "b": 0.0171629},
		{"obj_name": 5, "r": 89.8455, "g": 0.0381664, "b": 3.84651}
	]
},
{"uid": "P-85-4-0-4", "weight": 0.25, "r": 0, "g": 0, "b": 0, 
	"vertices": [
		{"obj_name": 4, "r": 38.5985, "g": 14.4766, "b": 161.205},
		{"obj_name": 5, "r": 34.2013, "g": 0.00510478, "b": 109.373},
		{"obj_name": 4, "r": 65.3269, "g": 81.5898, "b": 124.002},
		{"obj_name": 3, "r": 43.5971, "g": 0.00242179, "b": 60.5439},
		{"obj_name": 4, "r": 95.2573, "g": 42.839, "b": 169.99},
		{"obj_name": 0, "r": 18.4504, "g": 0.0115242, "b": 117.786},
		{"obj_name": 4, "r": 1.00179, "g": 25.2883, "b": 92.4451},
		{"obj_name": 5, "r": 12.6439, "g": 0.0071215, "b": 76.2314},
		{"obj_name": 1, "r": 83.0616, "g": 81.5904, "b": 110.504}
	]
},
{"uid": "P-85-4-0-5", "weight": 0.25, "r": 0, "g": 0, "b": 0, 
	"vertices": [
		{"obj_name": 4, "r": 38.5123, "g": 14.6887, "b": 161.153},
		{"obj_name": 3, "r": 33.9913, "g": 0.00483034, "b": 108.242},
		{"obj_name": 2, "r": 61.5748, "g": 23.0527, "b": 169.998},
		{"obj_name": 1, "r": 21.7093, "g": 53.9348, "b": 0.00486442},
		{"obj_name": 5, "r": 98.9916, "g": 51.8112, "b": 42.0417},
		{"obj_name": 1, "r": 94.5506, "g": 81.5724, "b": 22.1045}
	]
},
{"uid": "P-85-4-0-6", "weight": 0.25, "r": 0, "g": 0, "b": 0, 
	"vertices": [
		{"obj_name": 4, "r": 38.3252, "g": 14.6943, "b": 161.168},
		{"obj_name": 3, "r": 33.7282, "g": 0.00487081, "b": 108.234},
		{"obj_name": 1, "r": 87.8073, "g": 21.748, "b": 169.991},
		{"obj_name": 3, "r": 98.9901, "g": 38.1142, "b": 126.089},
		{"obj_name": 1, "r": 88.6772, "g": 34.4173, "b": 169.992},
		{"obj_name": 0, "r": 98.9669, "g": 44.6603, "b": 162.913},
		{"obj_name": 5, "r": 1.02131, "g": 77.2904, "b": 135.727}
	]
},
{"uid": "P-85-4-0-7", "weight": 0.25, "r": 0, "g": 0, "b": 0, 
	"vertices": [
		{"obj_name": 4, "r": 38.9723, "g": 14.6007, "b": 161.139},
		{"obj_name": 5, "r": 34.6685, "g": 0.00483735, "b": 108.663},
		{"obj_name": 0, "r": 92.5444, "g": 81.5824, "b": 122.916},
		{"obj_name": 4, "r": 1.03661, "g": 40.4038, "b": 167.166},
		{"obj_name": 1, "r": 50.0744, "g": 0.029828, "b": 158.837},
		{"obj_name": 4, "r": 98.9824, "g": 40.4091, "b": 140.857},
		{"obj_name": 5, "r": 49.9923, "g": 0.00294493, "b": 105.869},
		{"obj_name": 0, "r": 36.7669, "g": 81.5981, "b": 96.0086},
		{"obj_name": 1, "r": 1.00102, "g": 50.2862, "b": 70.9211}
	]
}
]}