{"paths": [
{"uid": "P-95-54-2-0", "weight": 0.25, "r": 0, "g": 0, "b": 0, 
	"vertices": [
		{"obj_name": 2, "r": 46.3472, "g": 54.0922, "b": 155.663},
		{"obj_name": 5, "r": 42.284, "g": 56.4194, "b": 0.00151751},
		{"obj_name": 2, "r": 81.4891, "g": 81.5632, "b": 1.84336},
		{"obj_name": 5, "r": 81.454, "g": 80.9874, "b": 0.0130219},
		{"obj_name": 1, "r": 80.137, "g": 81.5625, "b": 0.448292},
		{"obj_name": 2, "r": 98.9768, "g": 59.3443, "b": 16.0121},
		{"obj_name": 5, "r": 83.2759, "g": 53.7134, "b": 0.00637023},
		{"obj_name": 2, "r": 81.6227, "g": 81.5903, "b": 50.8254},
		{"obj_name": 1, "r": 86.022, "g": 61.1634, "b": 0.00856126},
		{"obj_name": 4, "r": 98.9906, "g": 2.81837, "b": 60.687},
		{"obj_name": 1, "r": 94.7011, "g": 0.0120329, "b": 61.3916},
		{"obj_name": 5, "r": 98.9968, "g": 23.5675, "b": 63.0872},
		{"obj_name": 2, "r": 79.5909, "g": 81.5891, "b": 45.3673}
	]
},
{"uid": "P-95-54-2-1", "weight": 0.25, "r": 0, "g": 0, "b": 0, 
	"vertices": [
		{"obj_name": 2, "r": 46.2103, "g": 54.0037, "b": 155.666},
		{"obj_name": 5, "r": 41.9947, "g": 56.2327, "b": 0.00151127},
		{"obj_name": 2, "r": 57.5788, "g": 81.5914, "b": 40.9032},
		{"obj_name": 0, "r": 49.7006, "g": 47.7313, "b": 0.000240664},
		{"obj_name": 4, "r": 1.0158, "g": 2.4478, "b": 40.4922},
		{"obj_name": 5, "r": 1.67728, "g": 0.0216289, "b": 36.9828},
		{"obj_name": 4, "r": 25.1562, "g": 81.5965, "b": 72.8547},
		{"obj_name": 3, "r": 27.9258, "g": 0.00765497, "b": 113.907}
	]
},
{"uid": "P-95-54-2-2", "weight": 0.25, "r": 0, "g": 0, "b": 0, 
	"vertices": [
		{"obj_name": 2, "r": 46.5141, "g": 53.8449, "b": 155.656},
		{"obj_name": 5, "r": 42.6368, "g": 55.8969, "b": 0.00141067},
		{"obj_name": 4, "r": 12.1076, "g": 81.5928, "b": 82.9619},
		{"obj_name": 5, "r": 16.7636, "g": 0.00640356, "b": 94.8686},
		{"obj_name": 2, "r": 33.0025, "g": 81.5681, "b": 3.49154},
		{"obj_name": 5, "r": 34.6881, "g": 49.0008, "b": 0.00150854}
	]
},
{"uid": "P-95-54-2-3", "weight": 0.25, "r": 0, "g": 0, "b": 0, 
	"vertices": [
		{"obj_name": 2, "r": 46.522, "g": 54.1254, "b": 155.659},
		{"obj_name": 5, "r": 42.6534, "g": 56.4896, "b": 0.00150068},
		{"obj_name": 6, "r": 26.7126, "g": 81.5773, "b": 18.3488},
		{"obj_name": 5, "r": 31.8513, "g": 32.0051, "b": 44.1177},
		{"obj_name": 1, "r": 70.8539, "g": 81.5939, "b": 53.7285},
		{"obj_name": 2, "r": 98.999, "g": 31.4966, "b": 70.5938},
		{"obj_name": 0, "r": 15.2145, "g": 36.8612, "b": 0.00612773}
	]
},
{"uid": "P-95-54-2-4", "weight": 0.25, "r": 0, "g": 0, "b": 0, 
	"vertices": [
		{"obj_name": 2, "r": 46.1057, "g": 53.8983, "b": 155.667},
		{"obj_name": 5, "r": 41.7736, "g": 56.01, "b": 0.0014951},
		{"obj_name": 6, "r": 18.3105, "g": 81.5655, "b": 4.76165},
		{"obj_name": 5, "r": 24.3997, "g": 32.6526, "b": 44.8595},
		{"obj_name": 1, "r": 14.9856, "g": 81.5928, "b": 67.2871},
		{"obj_name": 4, "r": 98.9747, "g": 39.0153, "b": 10.4855},
		{"obj_name": 6, "r": 23.826, "g": 0.0152358, "b": 32.9987},
		{"obj_name": 4, "r": 31.6441, "g": 2.5509, "b": 39.5097},
		{"obj_name": 6, "r": 41.8034, "g": 0.00752558, "b": 43.6799},
		{"obj_name": 1, "r": 40.8334, "g": 8.85186, "b": 42.268}
	]
},
{"uid": "P-95-54-2-5", "weight": 0.25, "r": 0, "g": 0, "b": 0, 
	"vertices": [
		{"obj_name": 2, "r": 46.2457, "g": 53.6789, "b": 155.66},
		{"obj_name": 0, "r": 42.0697, "g": 55.5464, "b": 0.00140174},
		{"obj_name": 2, "r": 1.02113, "g": 42.0875, "b": 16.6109},
		{"obj_name": 5, "r": 28.6348, "g": 74.2865, "b": 0.00788909},
		{"obj_name": 2, "r": 31.9809, "g": 81.5776, "b": 17.1929},
		{"obj_name": 5, "r": 16.549, "g": 63.8332, "b": 0.00824749}
	]
},
{"uid": "P-95-54-2-6", "weight": 0.25, "r": 0, "g": 0, "b": 0, 
	"vertices": [
		{"obj_name": 2, "r": 46.276, "g": 53.6335, "b": 155.659},
		{"obj_name": 5, "r": 42.1337, "g": 55.4505, "b": 0.00138257},
		{"obj_name": 2, "r": 27.5337, "g": 81.5776, "b": 18.5704},
		{"obj_name": 0, "r": 25.7141, "g": 68.0749, "b": 0.00666864},
		{"obj_name": 2, "r": 1.01631, "g": 24.7715, "b": 26.7783},
		{"obj_name": 6, "r": 7.48408, "g": 6.73259, "b": 0.014841},
		{"obj_name": 4, "r": 14.965, "g": 6.36959, "b": 42.0216},
		{"obj_name": 2, "r": 9.66331, "g": 0.0128494, "b": 50.8945},
		{"obj_name": 0, "r": 13.7634, "g": 72.583, "b": 0.0116163},
		{"obj_name": 2, "r": 1.0256, "g": 74.3085, "b": 18.3832},
		{"obj_name": 5, "r": 5.68341, "g": 79.1827, "b": 0.017186}
	]
},
{"uid": "P-95-54-2-7", "weight": 0.25, "r": 0, "g": 0, "b": 0, 
	"vertices": [
		{"obj_name": 2, "r": 46.6846, "g": 53.8133, "b": 155.651},
		{"obj_name": 5, "r": 42.9973, "g": 55.83, "b": 0.00137469},
		{"obj_name": 0, "r": 66.4378, "g": 81.5785, "b": 18.1621},
		{"obj_name": 5, "r": 1.0019, "g": 24.8218, "b": 92.7538},
		{"obj_name": 2, "r": 92.6741, "g": 81.5856, "b": 49.0476},
		{"obj_name": 0, "r": 89.8194, "g": 65.5223, "b": 0.0109839}
	]
}
]}